aipricepatterns/__init__.py
aipricepatterns/analysis.py
aipricepatterns/cli.py
aipricepatterns/client.py
aipricepatterns/validation.py
aipricepatterns-0.1.1.dist-info/METADATA
aipricepatterns-0.1.1.dist-info/WHEEL
aipricepatterns-0.1.1.dist-info/entry_points.txt
aipricepatterns-0.1.1.dist-info/top_level.txt
aipricepatterns-0.1.1.dist-info/RECORD
