Metadata-Version: 2.4
Name: aipricepatterns
Version: 0.1.1
Summary: Python client for AI Price Patterns API - Search engine for financial price action
Project-URL: Homepage, https://aipricepatterns.com
Project-URL: Bug Tracker, https://github.com/sergio12S/aipp/issues
Project-URL: Source, https://github.com/sergio12S/aipp
Classifier: Programming Language :: Python :: 3
Classifier: License :: OSI Approved :: MIT License
Classifier: Operating System :: OS Independent
Requires-Python: >=3.7
Requires-Dist: requests>=2.25.0
Requires-Dist: pandas>=1.0.0
Requires-Dist: numpy>=1.20.0
Requires-Dist: plotly>=5.0.0
Requires-Dist: matplotlib>=3.3.0
Requires-Dist: tqdm>=4.60.0
Requires-Dist: rich>=10.0.0
Provides-Extra: rl
Requires-Dist: stable-baselines3>=2.0.0; extra == "rl"
Requires-Dist: gymnasium>=0.26.0; extra == "rl"
Requires-Dist: shimmy>=0.2.1; extra == "rl"
Provides-Extra: research
Requires-Dist: jupyter>=1.0.0; extra == "research"
Requires-Dist: scikit-learn>=1.0.0; extra == "research"
